{"commitInfo":{"timestamp":1747113863742,"operation":"STREAMING UPDATE","operationParameters":{"outputMode":"Append","queryId":"c08bdc08-028f-4429-8e29-54fcecffbc78","epochId":"430"},"readVersion":429,"isolationLevel":"Serializable","isBlindAppend":true,"operationMetrics":{"numRemovedFiles":"0","numOutputRows":"1","numOutputBytes":"8103","numAddedFiles":"1"},"engineInfo":"Apache-Spark/3.5.5 Delta-Lake/3.1.0","txnId":"9486033f-eec2-4aa9-b292-9a79e03a1280"}}
{"txn":{"appId":"c08bdc08-028f-4429-8e29-54fcecffbc78","version":430,"lastUpdated":1747113863741}}
{"add":{"path":"part-00006-78914a7c-f2d2-4765-b46f-c50dde58f951-c000.snappy.parquet","partitionValues":{},"size":5835,"modificationTime":1747113857438,"dataChange":true,"stats":"{\"numRecords\":1,\"minValues\":{\"id\":12981,\"product_id\":9,\"customer_id\":14,\"branch_id\":15,\"quantity\":4,\"payment_method\":4,\"order_date\":\"2025-05-13T12:24:07.000+07:00\",\"order_status\":2.0,\"payment_status\":2.0,\"shipping_status\":2.0,\"delivery_fee\":31462,\"is_free_delivery_fee\":\"false\",\"created_at\":\"2025-05-13T12:24:07.000+07:00\",\"product_name\":\"Adidas Ultraboost\",\"product_category\":\"Apparel\",\"sub_category_product\":\"Footwear\",\"price\":3000000,\"amount\":12000000},\"maxValues\":{\"id\":12981,\"product_id\":9,\"customer_id\":14,\"branch_id\":15,\"quantity\":4,\"payment_method\":4,\"order_date\":\"2025-05-13T12:24:07.000+07:00\",\"order_status\":2.0,\"payment_status\":2.0,\"shipping_status\":2.0,\"delivery_fee\":31462,\"is_free_delivery_fee\":\"false\",\"created_at\":\"2025-05-13T12:24:07.000+07:00\",\"product_name\":\"Adidas Ultraboost\",\"product_category\":\"Apparel\",\"sub_category_product\":\"Footwear\",\"price\":3000000,\"amount\":12000000},\"nullCount\":{\"id\":0,\"product_id\":0,\"customer_id\":0,\"branch_id\":0,\"quantity\":0,\"payment_method\":0,\"order_date\":0,\"order_status\":0,\"payment_status\":0,\"shipping_status\":0,\"is_online_transaction\":0,\"delivery_fee\":0,\"is_free_delivery_fee\":0,\"created_at\":0,\"modified_at\":1,\"product_name\":0,\"product_category\":0,\"sub_category_product\":0,\"price\":0,\"disc\":1,\"disc_name\":1,\"amount\":0}}"}}
