{"commitInfo":{"timestamp":1747113387077,"operation":"STREAMING UPDATE","operationParameters":{"outputMode":"Append","queryId":"c08bdc08-028f-4429-8e29-54fcecffbc78","epochId":"394"},"readVersion":393,"isolationLevel":"Serializable","isBlindAppend":true,"operationMetrics":{"numRemovedFiles":"0","numOutputRows":"1","numOutputBytes":"8175","numAddedFiles":"1"},"engineInfo":"Apache-Spark/3.5.5 Delta-Lake/3.1.0","txnId":"4a2d0870-8223-4f4e-ba4a-42b73d5798b9"}}
{"txn":{"appId":"c08bdc08-028f-4429-8e29-54fcecffbc78","version":394,"lastUpdated":1747113387076}}
{"add":{"path":"part-00006-211000f3-47b8-4924-8fba-c88816f8a510-c000.snappy.parquet","partitionValues":{},"size":5907,"modificationTime":1747113381255,"dataChange":true,"stats":"{\"numRecords\":1,\"minValues\":{\"id\":12857,\"product_id\":7,\"customer_id\":88,\"branch_id\":20,\"quantity\":2,\"payment_method\":3,\"order_date\":\"2025-05-13T12:16:16.000+07:00\",\"order_status\":2.0,\"payment_status\":2.0,\"shipping_status\":2.0,\"delivery_fee\":31652,\"is_free_delivery_fee\":\"false\",\"created_at\":\"2025-05-13T12:16:16.000+07:00\",\"product_name\":\"Logitech MX Master 3\",\"product_category\":\"Electronics\",\"sub_category_product\":\"Accessories\",\"price\":1700000,\"amount\":3400000},\"maxValues\":{\"id\":12857,\"product_id\":7,\"customer_id\":88,\"branch_id\":20,\"quantity\":2,\"payment_method\":3,\"order_date\":\"2025-05-13T12:16:16.000+07:00\",\"order_status\":2.0,\"payment_status\":2.0,\"shipping_status\":2.0,\"delivery_fee\":31652,\"is_free_delivery_fee\":\"false\",\"created_at\":\"2025-05-13T12:16:16.000+07:00\",\"product_name\":\"Logitech MX Master 3\",\"product_category\":\"Electronics\",\"sub_category_product\":\"Accessories\",\"price\":1700000,\"amount\":3400000},\"nullCount\":{\"id\":0,\"product_id\":0,\"customer_id\":0,\"branch_id\":0,\"quantity\":0,\"payment_method\":0,\"order_date\":0,\"order_status\":0,\"payment_status\":0,\"shipping_status\":0,\"is_online_transaction\":0,\"delivery_fee\":0,\"is_free_delivery_fee\":0,\"created_at\":0,\"modified_at\":1,\"product_name\":0,\"product_category\":0,\"sub_category_product\":0,\"price\":0,\"disc\":1,\"disc_name\":1,\"amount\":0}}"}}
