{"commitInfo":{"timestamp":1747115435924,"operation":"STREAMING UPDATE","operationParameters":{"outputMode":"Append","queryId":"c08bdc08-028f-4429-8e29-54fcecffbc78","epochId":"505"},"readVersion":504,"isolationLevel":"Serializable","isBlindAppend":true,"operationMetrics":{"numRemovedFiles":"0","numOutputRows":"2","numOutputBytes":"8206","numAddedFiles":"1"},"engineInfo":"Apache-Spark/3.5.5 Delta-Lake/3.1.0","txnId":"317305d3-427e-4eb4-8992-c9b677b5572a"}}
{"txn":{"appId":"c08bdc08-028f-4429-8e29-54fcecffbc78","version":505,"lastUpdated":1747115435924}}
{"add":{"path":"part-00006-53cbf688-d4a6-4f24-8851-a28da793dc78-c000.snappy.parquet","partitionValues":{},"size":5938,"modificationTime":1747115419588,"dataChange":true,"stats":"{\"numRecords\":2,\"minValues\":{\"id\":13398,\"product_id\":1,\"customer_id\":67,\"branch_id\":8,\"quantity\":3,\"payment_method\":1,\"order_date\":\"2025-05-13T12:49:56.000+07:00\",\"order_status\":2.0,\"payment_status\":2.0,\"shipping_status\":2.0,\"delivery_fee\":0,\"is_free_delivery_fee\":\"true\",\"created_at\":\"2025-05-13T12:49:56.000+07:00\",\"product_name\":\"Logitech MX Master 3\",\"product_category\":\"Electronics\",\"sub_category_product\":\"Accessories\",\"price\":1700000,\"amount\":5100000},\"maxValues\":{\"id\":13403,\"product_id\":7,\"customer_id\":74,\"branch_id\":49,\"quantity\":3,\"payment_method\":2,\"order_date\":\"2025-05-13T12:50:06.000+07:00\",\"order_status\":2.0,\"payment_status\":2.0,\"shipping_status\":2.0,\"delivery_fee\":22180,\"is_free_delivery_fee\":\"true\",\"created_at\":\"2025-05-13T12:50:06.000+07:00\",\"product_name\":\"iPhone 15 Pro\",\"product_category\":\"Electronics\",\"sub_category_product\":\"Smartphones\",\"price\":15000000,\"amount\":45000000},\"nullCount\":{\"id\":0,\"product_id\":0,\"customer_id\":0,\"branch_id\":0,\"quantity\":0,\"payment_method\":0,\"order_date\":0,\"order_status\":0,\"payment_status\":0,\"shipping_status\":1,\"is_online_transaction\":0,\"delivery_fee\":0,\"is_free_delivery_fee\":1,\"created_at\":0,\"modified_at\":2,\"product_name\":0,\"product_category\":0,\"sub_category_product\":0,\"price\":0,\"disc\":2,\"disc_name\":2,\"amount\":0}}"}}
